create_ragbits_app/__init__.py
create_ragbits_app/main.py
create_ragbits_app/template_config_base.py
create_ragbits_app/template_utils.py
create_ragbits_app/ui.py
create_ragbits_app/ui_generator.py
create_ragbits_app/static/ui/react-ts/.gitignore.j2
create_ragbits_app/static/ui/react-ts/README.md.j2
create_ragbits_app/static/ui/react-ts/eslint.config.js.j2
create_ragbits_app/static/ui/react-ts/index.html.j2
create_ragbits_app/static/ui/react-ts/package.json.j2
create_ragbits_app/static/ui/react-ts/tsconfig.app.json.j2
create_ragbits_app/static/ui/react-ts/tsconfig.json.j2
create_ragbits_app/static/ui/react-ts/tsconfig.node.json.j2
create_ragbits_app/static/ui/react-ts/vite.config.ts.j2
create_ragbits_app/static/ui/react-ts/public/vite.svg.j2
create_ragbits_app/static/ui/react-ts/src/App.css.j2
create_ragbits_app/static/ui/react-ts/src/App.tsx.j2
create_ragbits_app/static/ui/react-ts/src/index.css.j2
create_ragbits_app/static/ui/react-ts/src/main.tsx.j2
create_ragbits_app/static/ui/react-ts/src/vite-env.d.ts.j2
create_ragbits_app/static/ui/react-ts/src/assets/react.svg.j2
create_ragbits_app/static/ui/vanilla-ts/.gitignore.j2
create_ragbits_app/static/ui/vanilla-ts/README.md.j2
create_ragbits_app/static/ui/vanilla-ts/index.html.j2
create_ragbits_app/static/ui/vanilla-ts/package.json.j2
create_ragbits_app/static/ui/vanilla-ts/tsconfig.json.j2
create_ragbits_app/static/ui/vanilla-ts/vite.config.ts.j2
create_ragbits_app/static/ui/vanilla-ts/public/vite.svg.j2
create_ragbits_app/static/ui/vanilla-ts/src/main.ts.j2
create_ragbits_app/templates/rag/.python-version.j2
create_ragbits_app/templates/rag/README.md.j2
create_ragbits_app/templates/rag/pyproject.toml.j2
create_ragbits_app/templates/rag/template_config.py
create_ragbits_app/templates/rag/docker/docker-compose.yml.j2
create_ragbits_app/templates/rag/src/{{pkg_name}}/__init__.py
create_ragbits_app/templates/rag/src/{{pkg_name}}/components.py.j2
create_ragbits_app/templates/rag/src/{{pkg_name}}/config.py.j2
create_ragbits_app-0.1.1.dist-info/METADATA
create_ragbits_app-0.1.1.dist-info/WHEEL
create_ragbits_app-0.1.1.dist-info/entry_points.txt
create_ragbits_app-0.1.1.dist-info/RECORD
