Metadata-Version: 2.4
Name: create-ragbits-app
Version: 0.1.1
Summary: Set up a modern LLM app by running one command
Requires-Python: >=3.11
Requires-Dist: aiohttp>=3.11.13
Requires-Dist: inquirer>=3.4.0
Requires-Dist: jinja2>=3.1.6
Requires-Dist: pydantic>=2.10.6
Requires-Dist: pyyaml<7.0.0,>=6.0.2
Requires-Dist: requests>=2.31.0
Requires-Dist: rich>=13.9.4
Requires-Dist: twine>=6.1.0
